{"song":{"sectionLengths":[],"player1":"bf","notes":[{"sectionNotes":[[0,2,0],[600,3,450],[1320,3,525]],"lengthInSteps":16,"typeOfSection":0,"mustHitSection":false},{"sectionNotes":[[2550,2,0],[3300,3,525],[3900,3,450]],"lengthInSteps":16,"typeOfSection":0,"mustHitSection":true},{"sectionNotes":[[5400,1,300],[6000,3,300],[6750,0,375]],"lengthInSteps":16,"typeOfSection":0,"mustHitSection":false},{"sectionNotes":[[8100,1,450],[8700,3,375],[9300,0,300]],"lengthInSteps":16,"typeOfSection":0,"mustHitSection":true},{"sectionNotes":[[10650,1,300],[11250,2,0],[11636.25,0,0]],"lengthInSteps":16,"typeOfSection":0,"mustHitSection":false},{"sectionNotes":[[12000,5,525],[13350,1,300],[13950,2,0]],"lengthInSteps":16,"typeOfSection":0,"mustHitSection":true},{"sectionNotes":[[14400,4,0],[14700,5,375],[16050,0,0],[16350,2,0],[16050,3,0],[16350,1,0]],"lengthInSteps":16,"typeOfSection":0,"mustHitSection":false},{"sectionNotes":[[16950,0,0],[17400,2,300],[18750,4,0],[19050,6,0]],"lengthInSteps":16,"typeOfSection":0,"mustHitSection":false},{"sectionNotes":[[19650,0,0],[19950,2,525],[21300,4,0]],"lengthInSteps":16,"typeOfSection":0,"mustHitSection":true},{"sectionNotes":[[21750,2,0],[22050,3,525]],"lengthInSteps":16,"typeOfSection":0,"mustHitSection":false},{"sectionNotes":[[24000,0,0],[24300,2,0],[24750,3,675]],"lengthInSteps":16,"typeOfSection":0,"mustHitSection":true},{"sectionNotes":[[26700,0,0],[27000,1,0],[27337.5,2,450]],"lengthInSteps":16,"typeOfSection":0,"mustHitSection":false},{"sectionNotes":[[29100,0,0],[29400,1,0],[29947.5,2,525]],"lengthInSteps":16,"typeOfSection":0,"mustHitSection":true},{"sectionNotes":[[31950,2,0],[32400,1,0],[32700,3,600]],"lengthInSteps":16,"typeOfSection":0,"mustHitSection":false},{"sectionNotes":[[34650,2,0],[34950,1,0],[35250,3,600]],"lengthInSteps":16,"typeOfSection":0,"mustHitSection":true},{"sectionNotes":[[37050,2,0],[37350,1,0],[37500,2,0],[37650,3,0]],"lengthInSteps":16,"typeOfSection":0,"mustHitSection":false},{"sectionNotes":[[38400,2,225],[38700,3,600],[39600,6,0],[39900,5,0],[40050,6,0],[40200,7,0]],"lengthInSteps":16,"typeOfSection":0,"mustHitSection":false},{"sectionNotes":[[40950,2,375],[41400,1,600],[42600,6,375]],"lengthInSteps":16,"typeOfSection":0,"mustHitSection":true},{"sectionNotes":[[43350,1,375],[44100,3,450],[45300,5,375]],"lengthInSteps":16,"typeOfSection":0,"mustHitSection":false},{"sectionNotes":[[46050,2,375],[46650,3,450]],"lengthInSteps":16,"typeOfSection":0,"mustHitSection":true},{"sectionNotes":[[48000,2,0],[48000,3,0],[48600,0,0],[49350,2,0],[49350,3,0],[49500,2,0],[49500,3,0],[49650,2,0],[49650,3,0],[49950,0,0]],"lengthInSteps":16,"typeOfSection":0,"mustHitSection":false},{"sectionNotes":[[50700,2,0],[50700,3,0],[51300,0,0],[52650,0,0],[52650,1,0],[51300,1,0],[52350,3,0],[52350,2,0],[52200,2,0],[52200,3,0],[52050,2,0],[52050,3,0]],"lengthInSteps":16,"typeOfSection":0,"mustHitSection":true},{"sectionNotes":[[53400,2,450],[54000,3,375],[54600,0,525]],"lengthInSteps":16,"typeOfSection":0,"mustHitSection":false},{"sectionNotes":[[55950,2,450],[56550,3,450],[57300,0,450]],"lengthInSteps":16,"typeOfSection":0,"mustHitSection":true},{"sectionNotes":[[58650,3,1425]],"lengthInSteps":16,"typeOfSection":0,"mustHitSection":false},{"sectionNotes":[[61350,3,1050]],"lengthInSteps":16,"typeOfSection":0,"mustHitSection":true},{"sectionNotes":[[64050,2,0],[64350,1,0]],"lengthInSteps":16,"typeOfSection":0,"mustHitSection":false},{"sectionNotes":[[64800,7,600],[66600,2,0],[66900,1,0]],"lengthInSteps":16,"typeOfSection":0,"mustHitSection":true},{"sectionNotes":[[67200,7,1200],[69000,2,0],[69300,1,0],[69450,2,0]],"lengthInSteps":16,"typeOfSection":0,"mustHitSection":false},{"sectionNotes":[[69600,3,0],[70350,2,300],[70736.25,1,600],[71700,6,0]],"lengthInSteps":16,"typeOfSection":0,"mustHitSection":false},{"sectionNotes":[[72000,1,0],[72150,2,0],[72300,3,0],[73050,2,0],[73200,1,525]],"lengthInSteps":16,"typeOfSection":0,"mustHitSection":true},{"sectionNotes":[[74700,7,0],[75000,5,0],[75300,7,0],[75600,6,0],[75900,4,525]],"lengthInSteps":16,"typeOfSection":0,"mustHitSection":true},{"typeOfSection":0,"sectionNotes":[[77400,3,0],[77700,1,0],[78000,3,0],[78300,2,0],[78450,1,600]],"lengthInSteps":16,"bpm":100,"changeBPM":false,"mustHitSection":true},{"lengthInSteps":16,"typeOfSection":0,"sectionNotes":[[79650,2,0],[79950,1,0],[80100,2,0],[80250,3,0],[81000,2,0],[81390,1,0],[81300,1,0],[81183.75,1,0],[81067.5,1,0]],"altAnim":false,"bpm":100,"changeBPM":false,"mustHitSection":false},{"lengthInSteps":16,"typeOfSection":0,"sectionNotes":[[81900,0,0],[82200,1,0],[82500,2,0],[82800,3,0]],"altAnim":false,"bpm":100,"changeBPM":false,"mustHitSection":true},{"lengthInSteps":16,"typeOfSection":0,"sectionNotes":[],"altAnim":false,"bpm":100,"changeBPM":false,"mustHitSection":true},{"sectionNotes":[],"typeOfSection":0,"lengthInSteps":16,"altAnim":false,"mustHitSection":true,"changeBPM":false,"bpm":100},{"lengthInSteps":16,"altAnim":false,"typeOfSection":0,"sectionNotes":[],"bpm":100,"changeBPM":false,"mustHitSection":true}],"player2":"dad","song":"Bopeebo","validScore":true,"sections":0,"needsVoices":true,"speed":1.6,"bpm":100}}